mvhs_schedule/__init__.py
mvhs_schedule/db.py
mvhs_schedule/models.py
mvhs_schedule/schedule.py
mvhs_schedule-0.1.0.dist-info/licenses/LICENSE
tests/test_schedule.py
mvhs_schedule-0.1.0.dist-info/METADATA
mvhs_schedule-0.1.0.dist-info/WHEEL
mvhs_schedule-0.1.0.dist-info/top_level.txt
mvhs_schedule-0.1.0.dist-info/RECORD
