Metadata-Version: 2.4
Name: mvhs-schedule
Version: 0.1.0
Summary: A library to fetch the MVHS Schedule.
Author: jt31415
Project-URL: Homepage, https://github.com/jt31415/mvhs-schedule
Project-URL: Bug Tracker, https://github.com/jt31415/mvhs-schedule/issues
Classifier: Programming Language :: Python :: 3
Classifier: License :: OSI Approved :: MIT License
Classifier: Operating System :: OS Independent
Requires-Python: >=3.10
License-File: LICENSE
Requires-Dist: httpx
Requires-Dist: platformdirs
Dynamic: license-file
